Metadata-Version: 2.1
Name: my-00077
Version: 0.1
Summary: Super usefull piece
Author: krisss
Author-email: kris@ex.ex
